MANIFEST.in
setup.py
sparkts/__init__.py
sparkts/_version.py
sparkts/datetimeindex.py
sparkts/sparkts-0.2.0-jar-with-dependencies.jar
sparkts/timeseriesrdd.py
sparkts/utils.py
sparkts.egg-info/PKG-INFO
sparkts.egg-info/SOURCES.txt
sparkts.egg-info/dependency_links.txt
sparkts.egg-info/requires.txt
sparkts.egg-info/top_level.txt
sparkts/test/__init__.py
sparkts/test/test_datetimeindex.py
sparkts/test/test_timeseriesrdd.py
sparkts/test/test_utils.py